LICENSE
MANIFEST.in
README.md
pyproject.toml
setup.py
nonebot_plugin_leetcode2/__init__.py
nonebot_plugin_leetcode2/get_problem_data.py
nonebot_plugin_leetcode2/get_user_data.py
nonebot_plugin_leetcode2.egg-info/PKG-INFO
nonebot_plugin_leetcode2.egg-info/SOURCES.txt
nonebot_plugin_leetcode2.egg-info/dependency_links.txt
nonebot_plugin_leetcode2.egg-info/requires.txt
nonebot_plugin_leetcode2.egg-info/top_level.txt
nonebot_plugin_leetcode2/template/template.html