Metadata-Version: 1.0
Name: nonebot-plugin-leetcode2
Version: 1.1.3
Summary: 基于nonebot2的leetcode查询插件。
Home-page: https://github.com/Nranphy/nonebot_plugin_leetcode2
Author: Nranphy
Author-email: 3102002900@qq.com
License: UNKNOWN
Platform: UNKNOWN
